X35SuiChengxuyuanDeTuiluLianghuaTouziXuexiBiji20210730Fix1/README.md
X35SuiChengxuyuanDeTuiluLianghuaTouziXuexiBiji20210730Fix1/__init__.py
X35SuiChengxuyuanDeTuiluLianghuaTouziXuexiBiji20210730Fix1/__main__.py
X35SuiChengxuyuanDeTuiluLianghuaTouziXuexiBiji20210730Fix1/file.epub
X35SuiChengxuyuanDeTuiluLianghuaTouziXuexiBiji20210730Fix1/index.html
X35SuiChengxuyuanDeTuiluLianghuaTouziXuexiBiji20210730Fix1/css/__init__.py
X35SuiChengxuyuanDeTuiluLianghuaTouziXuexiBiji20210730Fix1/css/annotations.css
X35SuiChengxuyuanDeTuiluLianghuaTouziXuexiBiji20210730Fix1/css/main.css
X35SuiChengxuyuanDeTuiluLianghuaTouziXuexiBiji20210730Fix1/css/normalize.css
X35SuiChengxuyuanDeTuiluLianghuaTouziXuexiBiji20210730Fix1/css/popup.css
X35SuiChengxuyuanDeTuiluLianghuaTouziXuexiBiji20210730Fix1/font/__init__.py
X35SuiChengxuyuanDeTuiluLianghuaTouziXuexiBiji20210730Fix1/font/fontello.eot
X35SuiChengxuyuanDeTuiluLianghuaTouziXuexiBiji20210730Fix1/font/fontello.svg
X35SuiChengxuyuanDeTuiluLianghuaTouziXuexiBiji20210730Fix1/font/fontello.ttf
X35SuiChengxuyuanDeTuiluLianghuaTouziXuexiBiji20210730Fix1/font/fontello.woff
X35SuiChengxuyuanDeTuiluLianghuaTouziXuexiBiji20210730Fix1/img/__init__.py
X35SuiChengxuyuanDeTuiluLianghuaTouziXuexiBiji20210730Fix1/img/annotator-glyph-sprite.png
X35SuiChengxuyuanDeTuiluLianghuaTouziXuexiBiji20210730Fix1/img/annotator-icon-sprite.png
X35SuiChengxuyuanDeTuiluLianghuaTouziXuexiBiji20210730Fix1/img/apple-touch-icon.png
X35SuiChengxuyuanDeTuiluLianghuaTouziXuexiBiji20210730Fix1/img/cancelfullscreen.png
X35SuiChengxuyuanDeTuiluLianghuaTouziXuexiBiji20210730Fix1/img/close.png
X35SuiChengxuyuanDeTuiluLianghuaTouziXuexiBiji20210730Fix1/img/fullscreen.png
X35SuiChengxuyuanDeTuiluLianghuaTouziXuexiBiji20210730Fix1/img/loader.gif
X35SuiChengxuyuanDeTuiluLianghuaTouziXuexiBiji20210730Fix1/img/menu-icon.png
X35SuiChengxuyuanDeTuiluLianghuaTouziXuexiBiji20210730Fix1/img/save.png
X35SuiChengxuyuanDeTuiluLianghuaTouziXuexiBiji20210730Fix1/img/saved.png
x35_sui_chengxuyuan_de_tuilu_lianghua_touzi_xuexi_biji_20210730_fix1-2025.3.25.0.dist-info/METADATA
x35_sui_chengxuyuan_de_tuilu_lianghua_touzi_xuexi_biji_20210730_fix1-2025.3.25.0.dist-info/WHEEL
x35_sui_chengxuyuan_de_tuilu_lianghua_touzi_xuexi_biji_20210730_fix1-2025.3.25.0.dist-info/entry_points.txt
x35_sui_chengxuyuan_de_tuilu_lianghua_touzi_xuexi_biji_20210730_fix1-2025.3.25.0.dist-info/top_level.txt
x35_sui_chengxuyuan_de_tuilu_lianghua_touzi_xuexi_biji_20210730_fix1-2025.3.25.0.dist-info/RECORD
